uit_tokenizer/UITws_v1.py
uit_tokenizer/__init__.py
uit_tokenizer-1.0.dist-info/LICENSE
uit_tokenizer-1.0.dist-info/METADATA
uit_tokenizer-1.0.dist-info/WHEEL
uit_tokenizer-1.0.dist-info/top_level.txt
uit_tokenizer-1.0.dist-info/RECORD
