Metadata-Version: 2.1
Name: uit-tokenizer
Version: 1.0
Summary: UITNLP: A Python NLP Library for Vietnamese
Home-page: https://github.com/it-dainb/uitnlp.git
Author: The UIT Natural Language Processing Group
Author-email: vund@uit.edu.vn
License: Apache License 2.0
Keywords: natural-language-processing nlp natural-language-understanding uit-nlp vietnamese-word-segmentation
Classifier: Topic :: Scientific/Engineering :: Artificial Intelligence
Classifier: Programming Language :: Python :: 3.6
Classifier: Programming Language :: Python :: 3.7
Classifier: Programming Language :: Python :: 3.8
Classifier: Programming Language :: Python :: 3.9
Classifier: Programming Language :: Python :: 3.10
Classifier: Programming Language :: Python :: 3.11
Requires-Python: >=3.6
License-File: LICENSE
Requires-Dist: sklearn
Requires-Dist: numpy
Requires-Dist: pandas
Requires-Dist: nltk
Requires-Dist: gdown
